LICENSE
MANIFEST.in
README.md
pyproject.toml
requirements.txt
setup.py
pycordSuperUtils/__init__.py
pycordSuperUtils/antispam.py
pycordSuperUtils/ban.py
pycordSuperUtils/base.py
pycordSuperUtils/birthday.py
pycordSuperUtils/client.py
pycordSuperUtils/commandhinter.py
pycordSuperUtils/convertors.py
pycordSuperUtils/database.py
pycordSuperUtils/economy.py
pycordSuperUtils/fivem.py
pycordSuperUtils/imaging.py
pycordSuperUtils/infractions.py
pycordSuperUtils/invitetracker.py
pycordSuperUtils/kick.py
pycordSuperUtils/leveling.py
pycordSuperUtils/messagefilter.py
pycordSuperUtils/modmail.py
pycordSuperUtils/mute.py
pycordSuperUtils/paginator.py
pycordSuperUtils/prefix.py
pycordSuperUtils/punishments.py
pycordSuperUtils/reactionroles.py
pycordSuperUtils/spotify.py
pycordSuperUtils/template.py
pycordSuperUtils/twitch.py
pycordSuperUtils/youtube.py
pycordSuperUtils.egg-info/PKG-INFO
pycordSuperUtils.egg-info/SOURCES.txt
pycordSuperUtils.egg-info/dependency_links.txt
pycordSuperUtils.egg-info/requires.txt
pycordSuperUtils.egg-info/top_level.txt
pycordSuperUtils/assets/1.png
pycordSuperUtils/assets/2.png
pycordSuperUtils/assets/3.png
pycordSuperUtils/assets/dnd.png
pycordSuperUtils/assets/font.ttf
pycordSuperUtils/assets/idle.png
pycordSuperUtils/assets/offline.png
pycordSuperUtils/assets/online.png
pycordSuperUtils/assets/spotify_black.png
pycordSuperUtils/assets/spotify_white.png
pycordSuperUtils/assets/streaming.png
pycordSuperUtils/music/__init__.py
pycordSuperUtils/music/constants.py
pycordSuperUtils/music/enums.py
pycordSuperUtils/music/exceptions.py
pycordSuperUtils/music/music.py
pycordSuperUtils/music/player.py
pycordSuperUtils/music/playlist.py
pycordSuperUtils/music/queue.py
pycordSuperUtils/music/utils.py
pycordSuperUtils/music/lavalink/__init__.py
pycordSuperUtils/music/lavalink/equalizer.py
pycordSuperUtils/music/lavalink/lavalink.py
pycordSuperUtils/music/lavalink/player.py