Metadata-Version: 2.1
Name: pycordSuperUtils
Version: 0.3.2
Summary: A fork of discordSuperUtils to easily develop discord Bots with pycord
Home-page: https://github.com/areoxy/pycord-super-utils
Author: koyashie07, adam7100 and Areo
License: MIT
Download-URL: https://github.com/areoxy/pycord-super-utils/archive/refs/tags/v0.3.2.tar.gz
Keywords: discord,easy,pycord,music,download,links,images,videos,audio,bot,paginator,economy,reaction,reaction roles,database,database manager
Platform: UNKNOWN
Classifier: Development Status :: 4 - Beta
Classifier: Intended Audience :: Developers
Classifier: Topic :: Software Development :: Build Tools
Classifier: License :: OSI Approved :: MIT License
Classifier: Programming Language :: Python :: 3
Classifier: Programming Language :: Python :: 3.4
Classifier: Programming Language :: Python :: 3.5
Classifier: Programming Language :: Python :: 3.6
Classifier: Programming Language :: Python :: 3.7
Classifier: Programming Language :: Python :: 3.9
Classifier: Programming Language :: Python :: 3.10
